fun/__init__.py
fun/bin/examples.py
fun/communications/__init__.py
fun/communications/communicator.py
fun/communications/contact_list.json
fun/communications/email_template.txt
fun/communications/liveline_logo.png
fun/communications/sms_email_stubs.json
fun/printing/__init__.py
fun/printing/formatted_console_print.py
fun_supergus-0.1.4.dist-info/LICENSE
fun_supergus-0.1.4.dist-info/METADATA
fun_supergus-0.1.4.dist-info/WHEEL
fun_supergus-0.1.4.dist-info/top_level.txt
fun_supergus-0.1.4.dist-info/RECORD
