Metadata-Version: 2.1
Name: fun-supergus
Version: 0.1.4
Summary: Toolkit for various fun and useful tasks
Home-page: https://github.com/supergus/fun
Author: Christopher Couch
Author-email: christopher.couch@gmail.com
License: LICENSE
Project-URL: Source, https://github.com/supergus/fun
Keywords: fun utilities email SMS
Platform: UNKNOWN
Classifier: Intended Audience :: Developers
Classifier: Topic :: Scientific/Engineering :: Artificial Intelligence
Classifier: Programming Language :: Python :: 3.7
Classifier: License :: OSI Approved :: MIT License
Classifier: Operating System :: OS Independent
Classifier: Development Status :: 4 - Beta
Classifier: Natural Language :: English
Requires-Python: >=3.7
